[
  {
    "name": "Огородный Тяпка",
    "description": "Тяпка огород приносить радость",
    "base_cost": 1000,
    "cost_modifier": 2,
    "max_level": 0,
    "effect": "При первой покупке разрешает автосбор: 1 час, 200 рис в час. Дальше — Автосбор 10 минут",
    "image": ""
  },
  {
    "name": "Телескоп для смартфона",
    "description": "Видеть рис издалека",
    "base_cost": 3000,
    "cost_modifier": 1.5,
    "max_level": 0,
    "effect": "2% к сбору Рис",
    "image": ""
  },
  {
    "name": "Массажёр для лоб",
    "description": "Помогает думать о Партия",
    "base_cost": 2500,
    "cost_modifier": 1.5,
    "max_level": 0,
    "effect": "2% к времени автосбора, 2% к объёму автосбора",
    "image": ""
  },
  {
    "name": "Отпуск остров Хайнань",
    "description": "Отдохнуть и продолжать трудиться",
    "base_cost": 5000,
    "cost_modifier": 1.4,
    "max_level": 0,
    "effect": "5% к сбору рис",
    "image": ""
  },
  {
    "name": "Кошко-жена",
    "description": "Лучшее, что вы можете получить от Партия",
    "base_cost": 20000,
    "cost_modifier": 1.5,
    "max_level": 0,
    "effect": "Автосбор 500 рис в час, 10% к сбору рис",
    "image": ""
  },
  {
    "name": "Кепка с Вентилятор",
    "description": "Прохлаждайся, пока работаешь",
    "base_cost": 10000,
    "cost_modifier": 1.5,
    "max_level": 0,
    "effect": "10% к времени автосбора, 10% к объёму автосбора",
    "image": ""
  },
  {
    "name": "Зарядка на солнечной энергии",
    "description": "Заряди себя и друзей",
    "base_cost": 10000,
    "cost_modifier": 1.4,
    "max_level": 0,
    "effect": "x2 к бонусу за привлечение друга",
    "image": ""
  }
]
